dependency_injection_pattern-0.0.5.dist-info/licenses/LICENSE
di/__init__.py
di/exceptions.py
di/core/container.py
di/core/default_scope.py
di/core/factory.py
di/core/helpers.py
di/core/log.py
di/core/named_service.py
di/core/provider.py
di/core/scope.py
di/core/service_request.py
di/core/exceptions/add_exception.py
di/core/exceptions/container_sealed_error.py
di/core/exceptions/factory_provide_exception.py
di/core/exceptions/implementation_exception.py
di/core/exceptions/provide_exception.py
di/core/exceptions/seal_exception.py
di/core/factories/dependency.py
di/core/factories/factory.py
di/core/factories/scoped_factory.py
di/core/factories/singleton_factory.py
di/core/factories/transient_factory.py
di/core/protocols/container.py
di/core/protocols/factory.py
di/core/protocols/provider.py
dependency_injection_pattern-0.0.5.dist-info/METADATA
dependency_injection_pattern-0.0.5.dist-info/WHEEL
dependency_injection_pattern-0.0.5.dist-info/top_level.txt
dependency_injection_pattern-0.0.5.dist-info/RECORD
